essa/__init__.py
essa/basic_decompose.py
essa/decompose.py
essa/reconstruct.py
essa/toeplitz_decompose.py
essa-0.3.dist-info/licenses/LICENSE
tests/__init__.py
tests/test_ssa.py
essa-0.3.dist-info/METADATA
essa-0.3.dist-info/WHEEL
essa-0.3.dist-info/top_level.txt
essa-0.3.dist-info/RECORD
