Metadata-Version: 2.4
Name: essa
Version: 0.3
Summary: Easy Singular Spectrum Analysis (SSA) implementation for Python
Home-page: https://github.com/ProtonEvgeny/essa
Author: Eugene Turov
Author-email: linker0broadcast@gmail.com
Classifier: Programming Language :: Python :: 3
Classifier: Intended Audience :: Science/Research
Classifier: License :: OSI Approved :: MIT License
Classifier: Operating System :: OS Independent
Classifier: Topic :: Scientific/Engineering :: Mathematics
Requires-Python: >=3.9
License-File: LICENSE
Requires-Dist: numpy>=2.0.0
Requires-Dist: scipy>=1.11.0
Requires-Dist: scikit-learn>=1.5.0
Dynamic: author
Dynamic: author-email
Dynamic: classifier
Dynamic: description
Dynamic: description-content-type
Dynamic: home-page
Dynamic: license-file
Dynamic: requires-dist
Dynamic: requires-python
Dynamic: summary
